gg8lib/__init__.py
gg8lib-1.1.6.dist-info/METADATA
gg8lib-1.1.6.dist-info/WHEEL
gg8lib-1.1.6.dist-info/licenses/LICENSE
gg8lib-1.1.6.dist-info/RECORD
