Metadata-Version: 2.1
Name: gg8lib
Version: 1.1.6
Summary: A small package containing: Progress Bars, Selection Prompts, String Selection and more! Use gg8lib.interactive_help() for a better understanding.
Project-URL: Homepage, https://gloriousglider8.github.io/gg8lib
Project-URL: Issues, https://github.com/GloriousGlider8/gg8lib/issues
Author-email: Sam Plimmer <sam.g.plimmer@gmail.com>
License-File: LICENSE
Classifier: License :: OSI Approved :: MIT License
Classifier: Operating System :: OS Independent
Classifier: Programming Language :: Python :: 3
Requires-Python: >=3.8
